PlotScrollNumpyArrays/PlotScroll.py
PlotScrollNumpyArrays/Plot_Scroll_Images.py
PlotScrollNumpyArrays/__init__.py
PlotScrollNumpyArrays-2.0.11.dist-info/METADATA
PlotScrollNumpyArrays-2.0.11.dist-info/WHEEL
PlotScrollNumpyArrays-2.0.11.dist-info/top_level.txt
PlotScrollNumpyArrays-2.0.11.dist-info/RECORD
