Metadata-Version: 2.1
Name: PlotScrollNumpyArrays
Version: 2.0.11
Summary: Services for plotting and viewing
Home-page: https://github.com/brianmanderson/Dicom_RT_and_Images_to_Mask
Author: Brian Mark Anderson
Author-email: markba122@gmail.com
Classifier: Programming Language :: Python :: 3
Classifier: License :: OSI Approved :: GNU Affero General Public License v3
Requires-Dist: numpy
Requires-Dist: matplotlib
Requires-Dist: SimpleITK
